moom/__init__.py
moom/api.py
moom/quotes.csv
moom-0.2.1.dist-info/LICENSE
moom-0.2.1.dist-info/METADATA
moom-0.2.1.dist-info/WHEEL
moom-0.2.1.dist-info/top_level.txt
moom-0.2.1.dist-info/RECORD
