Metadata-Version: 2.1
Name: moom
Version: 0.2.1
Summary: Useless Quotes for Controls Engineers
Author-email: "\"Iscito <>\"" <hutcheb@iscito.com>
Project-URL: Repository, https://github.com/iscito/moom
Keywords: moom,controls,engineer,SCADA,PLC
Classifier: Development Status :: 3 - Alpha
Classifier: License :: OSI Approved :: GNU General Public License v3 or later (GPLv3+)
Classifier: Programming Language :: Python :: 3.12
Classifier: Topic :: Scientific/Engineering :: Artificial Intelligence
License-File: LICENSE
Provides-Extra: dev
Requires-Dist: pytest-asyncio>=0.18.3; extra == "dev"
Requires-Dist: pip-tools; extra == "dev"
Requires-Dist: black; extra == "dev"
Requires-Dist: pip; extra == "dev"
Requires-Dist: deptry; extra == "dev"
Requires-Dist: requires; extra == "dev"
Requires-Dist: pre-commit>=2.6.0; extra == "dev"
Requires-Dist: pytest-mock>=3.8.1; extra == "dev"
Requires-Dist: mock>=4.0.2; extra == "dev"
Requires-Dist: mypy>=0.942; extra == "dev"
Requires-Dist: flake8>=4.0.1; extra == "dev"
Requires-Dist: pytest-asyncio; extra == "dev"
